MANIFEST.in
README.rst
bootstrap.py
buildout.cfg
setup.py
matlab/cg_based/demoflow.m
matlab/cg_based/flowimage.m
matlab/cg_based/flowmovie.m
matlab/cg_based/readme.txt
matlab/cg_based/mex/Coarse2FineTwoFrames.cpp
matlab/cg_based/mex/Coarse2FineTwoFrames.m
matlab/cg_based/mex/GaussianPyramid.cpp
matlab/cg_based/mex/GaussianPyramid.h
matlab/cg_based/mex/Image.h
matlab/cg_based/mex/ImageIO.h
matlab/cg_based/mex/ImageProcessing.h
matlab/cg_based/mex/OpticalFlow.cpp
matlab/cg_based/mex/OpticalFlow.h
matlab/cg_based/mex/project.h
matlab/sor_based/flowimage.m
matlab/sor_based/flowmovie.m
matlab/sor_based/readme.txt
matlab/sor_based/mex/Coarse2FineTwoFrames.asv
matlab/sor_based/mex/Coarse2FineTwoFrames.cpp
matlab/sor_based/mex/Coarse2FineTwoFrames.m
matlab/sor_based/mex/GaussianPyramid.cpp
matlab/sor_based/mex/GaussianPyramid.h
matlab/sor_based/mex/Image.h
matlab/sor_based/mex/ImageIO.h
matlab/sor_based/mex/ImageProcessing.h
matlab/sor_based/mex/Matrix.h
matlab/sor_based/mex/NoiseModel.h
matlab/sor_based/mex/OpticalFlow.cpp
matlab/sor_based/mex/OpticalFlow.h
matlab/sor_based/mex/Stochastic.cpp
matlab/sor_based/mex/Stochastic.h
matlab/sor_based/mex/Vector.h
matlab/sor_based/mex/project.h
xbob/__init__.py
xbob.optflow.liu.egg-info/PKG-INFO
xbob.optflow.liu.egg-info/SOURCES.txt
xbob.optflow.liu.egg-info/dependency_links.txt
xbob.optflow.liu.egg-info/entry_points.txt
xbob.optflow.liu.egg-info/namespace_packages.txt
xbob.optflow.liu.egg-info/not-zip-safe
xbob.optflow.liu.egg-info/requires.txt
xbob.optflow.liu.egg-info/top_level.txt
xbob/optflow/__init__.py
xbob/optflow/liu/__init__.py
xbob/optflow/liu/test.py
xbob/optflow/liu/version.py
xbob/optflow/liu/cg_based/GaussianPyramid.cpp
xbob/optflow/liu/cg_based/GaussianPyramid.h
xbob/optflow/liu/cg_based/Image.h
xbob/optflow/liu/cg_based/ImageProcessing.h
xbob/optflow/liu/cg_based/OpticalFlow.cpp
xbob/optflow/liu/cg_based/OpticalFlow.h
xbob/optflow/liu/cg_based/ext.cpp
xbob/optflow/liu/cg_based/project.h
xbob/optflow/liu/data/color/car1.png
xbob/optflow/liu/data/color/car2.png
xbob/optflow/liu/data/color/rubberwhale1.png
xbob/optflow/liu/data/color/rubberwhale2.png
xbob/optflow/liu/data/color/table1.png
xbob/optflow/liu/data/color/table2.png
xbob/optflow/liu/data/gray/car1.png
xbob/optflow/liu/data/gray/car2.png
xbob/optflow/liu/data/gray/complex1.png
