Metadata-Version: 1.1
Name: xbob.optflow.liu
Version: 1.1.2
Summary: Python bindings to the optical flow framework by C. Liu
Home-page: http://pypi.python.org/pypi/xbob.optflow.liu
Author: Andre Anjos
Author-email: andre.anjos@idiap.ch
License: GPLv3
Platform: UNKNOWN
Classifier: Development Status :: 4 - Beta
Classifier: Intended Audience :: Developers
Classifier: License :: OSI Approved :: GNU General Public License v3 (GPLv3)
Classifier: Natural Language :: English
Classifier: Programming Language :: Python
Classifier: Topic :: Scientific/Engineering :: Artificial Intelligence
Classifier: Topic :: Scientific/Engineering :: Image Recognition
